strfilter/__init__.py
strfilter/strfilter.py
strfilter-2.0.0.dist-info/LICENSE.txt
strfilter-2.0.0.dist-info/METADATA
strfilter-2.0.0.dist-info/WHEEL
strfilter-2.0.0.dist-info/top_level.txt
strfilter-2.0.0.dist-info/RECORD
