Metadata-Version: 2.1
Name: strfilter
Version: 2.0.0
Summary: A (simple) package for filtering text based on an input
Home-page: UNKNOWN
Author: Rizwan Niju
Author-email: mohammed.r210@outlook.com
License: UNKNOWN
Platform: UNKNOWN
Classifier: Programming Language :: Python :: 3
Classifier: License :: OSI Approved :: MIT License
Classifier: Operating System :: OS Independent
Requires-Python: >=3.10
License-File: LICENSE.txt
